Pysimxrd/CGCNN_atom_emb.json
Pysimxrd/__init__.py
Pysimxrd/generator.py
Pysimxrd/utils/MatgenKit.py
Pysimxrd/utils/WPEMsim.py
Pysimxrd/utils/funs.py
Pysimxrd-0.1.1.dist-info/METADATA
Pysimxrd-0.1.1.dist-info/WHEEL
Pysimxrd-0.1.1.dist-info/top_level.txt
Pysimxrd-0.1.1.dist-info/RECORD
