Metadata-Version: 2.1
Name: Pysimxrd
Version: 0.1.1
Summary: XRD simulator
Home-page: https://github.com/Bin-Cao/SimXRD
Author: CaoBin
Author-email: binjacobcao@gmail.com
Maintainer: CaoBin
Maintainer-email: binjacobcao@gmail.com
License: MIT License
Classifier: Development Status :: 3 - Alpha
Classifier: Intended Audience :: Developers
Classifier: Topic :: Software Development :: Build Tools
Classifier: License :: OSI Approved :: MIT License
Classifier: Programming Language :: Python :: 3
Classifier: Programming Language :: Python :: 3.5
Classifier: Programming Language :: Python :: 3.6
Classifier: Programming Language :: Python :: 3.7
Classifier: Programming Language :: Python :: 3.8
Classifier: Programming Language :: Python :: 3.9
Requires-Python: >=3.5
Requires-Dist: scipy
Requires-Dist: ase
Requires-Dist: pymatgen
